docs/Makefile
docs/api.rst
docs/changelog.rst
docs/cli.rst
docs/conf.py
docs/contributing.rst
docs/index.rst
docs/library.rst
docs/requirements.txt
docs/tables.rst
spoonbill/__init__.py
spoonbill/cli.py
spoonbill/common.py
spoonbill/flatten.py
spoonbill/i18n.py
spoonbill/rowdata.py
spoonbill/spec.py
spoonbill/stats.py
spoonbill/utils.py
spoonbill/locale/messages.pot
spoonbill/locale/en/LC_MESSAGES/spoonbill.mo
spoonbill/locale/en/LC_MESSAGES/spoonbill.po
spoonbill/locale/es/LC_MESSAGES/spoonbill.mo
spoonbill/locale/es/LC_MESSAGES/spoonbill.po
spoonbill/writers/__init__.py
spoonbill/writers/base_writer.py
spoonbill/writers/csv.py
spoonbill/writers/xlsx.py
spoonbill-1.1.0.dist-info/LICENSE
spoonbill-1.1.0.dist-info/METADATA
spoonbill-1.1.0.dist-info/WHEEL
spoonbill-1.1.0.dist-info/entry_points.txt
spoonbill-1.1.0.dist-info/top_level.txt
spoonbill-1.1.0.dist-info/RECORD
