Metadata-Version: 2.1
Name: spoonbill
Version: 1.1.0
Summary: Converts data that conforms to the Open Contracting Data Standard from JSON to Excel / CSV
Author-email: Open Contracting Partnership <data@open-contracting.org>
License: BSD
Project-URL: Homepage, https://github.com/open-contracting/spoonbill
Classifier: License :: OSI Approved :: BSD License
Classifier: Operating System :: OS Independent
Classifier: Programming Language :: Python :: 3.9
Classifier: Programming Language :: Python :: 3.10
Classifier: Programming Language :: Python :: 3.11
Classifier: Programming Language :: Python :: 3.12
Classifier: Programming Language :: Python :: Implementation :: CPython
License-File: LICENSE
Requires-Dist: click
Requires-Dist: click-logging
Requires-Dist: flatten-dict
Requires-Dist: ijson >=2.5
Requires-Dist: jsonref
Requires-Dist: ocdsextensionregistry
Requires-Dist: ocdskit >=1.0.1
Requires-Dist: requests
Requires-Dist: scalpl
Requires-Dist: xlsxwriter
Requires-Dist: importlib-resources ; python_version < "3.12"
Requires-Dist: dataclasses ; python_version < "3.7"
Provides-Extra: test
Requires-Dist: coverage ; extra == 'test'
Requires-Dist: jmespath ; extra == 'test'
Requires-Dist: jsonpointer ; extra == 'test'
Requires-Dist: openpyxl ; extra == 'test'
Requires-Dist: pytest ; extra == 'test'
